nanorpc/__init__.py
nanorpc/client.py
nanorpc/client_dynamic.py
nanorpc/client_nanoto.py
nanorpc/versions/__init__.py
nanorpc/versions/handler.py
nanorpc/versions/nano_to.py
nanorpc/versions/undocumented.py
nanorpc/versions/v23_3.py
nanorpc/versions/v24_0.py
nanorpc/versions/v25_0.py
nanorpc/versions/v27_1.py
nanorpc/versions/v28_0.py
nanorpc-0.28.0.dist-info/METADATA
nanorpc-0.28.0.dist-info/WHEEL
nanorpc-0.28.0.dist-info/top_level.txt
nanorpc-0.28.0.dist-info/RECORD
