Metadata-Version: 2.4
Name: nanorpc
Version: 0.28.0
Summary: async nano rpc library with dynamic method generation per node version
Author: gr0vity
License: MIT License
Project-URL: Homepage, https://github.com/gr0vity-dev/nano-rpc-py
Project-URL: Repository, https://github.com/gr0vity-dev/nano-rpc-py
Classifier: Development Status :: 4 - Beta
Classifier: Intended Audience :: Developers
Classifier: License :: OSI Approved :: MIT License
Classifier: Programming Language :: Python :: 3
Classifier: Programming Language :: Python :: 3.7
Classifier: Programming Language :: Python :: 3.8
Classifier: Programming Language :: Python :: 3.9
Classifier: Programming Language :: Python :: 3.10
Classifier: Programming Language :: Python :: 3.11
Classifier: Programming Language :: Python :: 3.12
Requires-Python: >=3.7
Requires-Dist: aiohttp
